pyscaffoldext/travis/__init__.py
pyscaffoldext/travis/extension.py
pyscaffoldext/travis/templates/__init__.py
pyscaffoldext/travis/templates/travis.template
pyscaffoldext/travis/templates/travis_install.template
pyscaffoldext_travis-0.3.dist-info/AUTHORS.rst
pyscaffoldext_travis-0.3.dist-info/LICENSE.txt
pyscaffoldext_travis-0.3.dist-info/METADATA
pyscaffoldext_travis-0.3.dist-info/WHEEL
pyscaffoldext_travis-0.3.dist-info/entry_points.txt
pyscaffoldext_travis-0.3.dist-info/top_level.txt
pyscaffoldext_travis-0.3.dist-info/RECORD
